smqtk/__init__.py
smqtk/compute_functions.py
smqtk/algorithms/__init__.py
smqtk/algorithms/classifier/__init__.py
smqtk/algorithms/classifier/index_label.py
smqtk/algorithms/classifier/libsvm.py
smqtk/algorithms/descriptor_generator/__init__.py
smqtk/algorithms/descriptor_generator/caffe_descriptor.py
smqtk/algorithms/descriptor_generator/colordescriptor/INSTALL.md
smqtk/algorithms/descriptor_generator/colordescriptor/__init__.py
smqtk/algorithms/descriptor_generator/colordescriptor/colordescriptor.py
smqtk/algorithms/descriptor_generator/colordescriptor/encode_FLANN.py
smqtk/algorithms/descriptor_generator/colordescriptor/utils.py
smqtk/algorithms/descriptor_generator/kwcnndescriptor/LICENSE
smqtk/algorithms/descriptor_generator/kwcnndescriptor/__init__.py
smqtk/algorithms/descriptor_generator/kwcnndescriptor/kwcnndescriptor.py
smqtk/algorithms/descriptor_generator/kwcnndescriptor/kwcnnmodel.npy
smqtk/algorithms/nn_index/__init__.py
smqtk/algorithms/nn_index/faiss.py
smqtk/algorithms/nn_index/flann.py
smqtk/algorithms/nn_index/mrpt.py
smqtk/algorithms/nn_index/hash_index/__init__.py
smqtk/algorithms/nn_index/hash_index/linear.py
smqtk/algorithms/nn_index/hash_index/sklearn_balltree.py
smqtk/algorithms/nn_index/lsh/__init__.py
smqtk/algorithms/nn_index/lsh/functors/__init__.py
smqtk/algorithms/nn_index/lsh/functors/itq.py
smqtk/algorithms/nn_index/lsh/functors/simple_rp.py
smqtk/algorithms/relevancy_index/__init__.py
smqtk/algorithms/relevancy_index/libsvm_hik.py
smqtk/bin/__init__.py
smqtk/bin/check_images.py
smqtk/bin/classifier_kfold_validation.py
smqtk/bin/classifier_model_validation.py
smqtk/bin/classifyFiles.py
smqtk/bin/computeDescriptor.py
smqtk/bin/compute_classifications.py
smqtk/bin/compute_hash_codes.py
smqtk/bin/compute_many_descriptors.py
smqtk/bin/createFileIngest.py
smqtk/bin/createGirderIngest.py
smqtk/bin/descriptors_to_svmtrainfile.py
smqtk/bin/generate_image_transform.py
smqtk/bin/iqrTrainClassifier.py
smqtk-0.7.0.dist-info/DESCRIPTION.rst
smqtk-0.7.0.dist-info/METADATA
smqtk-0.7.0.dist-info/RECORD
smqtk-0.7.0.dist-info/WHEEL
smqtk-0.7.0.dist-info/entry_points.txt
smqtk-0.7.0.dist-info/metadata.json
smqtk-0.7.0.dist-info/top_level.txt
